smoke_test/__init__.py
smoke_test/constants.py
smoke_test/fixtures.py
smoke_test/main.py
smoke_test/shell.py
smoke_test/utils.py
smoke_test/tests/__init__.py
smoke_test/tests/base.py
smoke_test/tests/code_analysis.py
smoke_test/tests/functional/__init__.py
smoke_test/tests/functional/base.py
smoke_test/tests/functional/file.py
smoke_test/tests/functional/mixins.py
smoke_test/tests/functional/stdio.py
smoke_test-1.1.0.dist-info/AUTHORS
smoke_test-1.1.0.dist-info/LICENSE
smoke_test-1.1.0.dist-info/METADATA
smoke_test-1.1.0.dist-info/WHEEL
smoke_test-1.1.0.dist-info/entry_points.txt
smoke_test-1.1.0.dist-info/top_level.txt
smoke_test-1.1.0.dist-info/RECORD
