Metadata-Version: 2.1
Name: smoke-test
Version: 1.1.0
Summary: Console app and Python API for automated smoke testing
Home-page: https://github.com/petarmaric/smoke_test
Author: Petar Maric
Author-email: petarmaric@uns.ac.rs
License: BSD
Platform: UNKNOWN
Classifier: Development Status :: 5 - Production/Stable
Classifier: Environment :: Console
Classifier: Intended Audience :: Developers
Classifier: Intended Audience :: Education
Classifier: License :: OSI Approved :: BSD License
Classifier: Operating System :: OS Independent
Classifier: Programming Language :: Python :: 2.7
Classifier: Topic :: Education
Classifier: Topic :: Utilities
Requires-Dist: friendly-name-mixin (~=1.0)
Requires-Dist: pycparser (==2.19)
Requires-Dist: pycparser-fake-libc (==2.19)
Requires-Dist: PyYAML (~=3.11)
Requires-Dist: simple-plugins (~=1.0)
Provides-Extra: dev
Requires-Dist: pex (~=1.6.0) ; extra == 'dev'
